classic/container/__init__.py
classic/container/builder.py
classic/container/constants.py
classic/container/container.py
classic/container/registry.py
classic/container/settings.py
classic/container/types.py
classic_container-0.7.5.dist-info/licenses/LICENSE
classic_container-0.7.5.dist-info/METADATA
classic_container-0.7.5.dist-info/WHEEL
classic_container-0.7.5.dist-info/top_level.txt
classic_container-0.7.5.dist-info/RECORD
