Metadata-Version: 2.4
Name: classic-container
Version: 0.7.5
Summary: Utilites for composites layer
Author-email: Sergey Variasov <variasov@gmail.com>
Project-URL: Homepage, https://github.com/variasov/classic-container
Requires-Python: >=3.10
License-File: LICENSE
Provides-Extra: dev
Requires-Dist: build~=1.2.2.post1; extra == "dev"
Requires-Dist: pytest==8.3.4; extra == "dev"
Requires-Dist: pytest-cov==6.0.0; extra == "dev"
Requires-Dist: twine~=4.0; extra == "dev"
Provides-Extra: debug
Requires-Dist: traceback-with-variables~=2.0; extra == "debug"
Dynamic: license-file
